virtueai/__init__.py
virtueai/cli/__init__.py
virtueai/cli/databricks_guard_interactive_demo.py
virtueai/guard/__init__.py
virtueai/guard/databricks_guard.py
virtueai/guard/openai_runhook.py
virtueai/guard/together_safety_model.py
virtueai/guard/virtue_guard_agent.py
virtueai/models/__init__.py
virtueai/models/databrics.py
virtueai/models/safety_model.py
virtueai/models/virtueai.py
virtueai/utils/__init__.py
virtueai/utils/logger.py
virtueai-0.2.0.dist-info/licenses/LICENSE
virtueai-0.2.0.dist-info/METADATA
virtueai-0.2.0.dist-info/WHEEL
virtueai-0.2.0.dist-info/entry_points.txt
virtueai-0.2.0.dist-info/top_level.txt
virtueai-0.2.0.dist-info/RECORD
