Metadata-Version: 2.4
Name: virtueai
Version: 0.2.0
Summary: VirtueAI Python package
Requires-Python: >=3.8
License-File: LICENSE
Requires-Dist: openai>=2.8.1
Requires-Dist: together>=1.5.30
Requires-Dist: prompt-toolkit>=3.0.0
Requires-Dist: mlflow>=3.7.0
Provides-Extra: dev
Requires-Dist: pytest>=7.0; extra == "dev"
Requires-Dist: black>=23.0; extra == "dev"
Requires-Dist: ruff>=0.1.0; extra == "dev"
Dynamic: license-file
